simpleruleengine/__init__.py
simpleruleengine/test_expression.py
simpleruleengine/test_expression_builder.py
simpleruleengine/test_operator.py
simpleruleengine/test_rule_decision.py
simpleruleengine/test_rule_row_decision.py
simpleruleengine/test_rule_row_score.py
simpleruleengine/test_rule_score.py
simpleruleengine/test_rule_set_decision.py
simpleruleengine/test_rule_set_score.py
simpleruleengine/test_when_all.py
simpleruleengine/test_when_any.py
simpleruleengine/conditional/__init__.py
simpleruleengine/conditional/conditional.py
simpleruleengine/conditional/when_all.py
simpleruleengine/conditional/when_any.py
simpleruleengine/exception/__init__.py
simpleruleengine/exception/rule_row_exceptions.py
simpleruleengine/expression/__init__.py
simpleruleengine/expression/expression.py
simpleruleengine/expression/expression_builder.py
simpleruleengine/operator/__init__.py
simpleruleengine/operator/between.py
simpleruleengine/operator/boolean_operator.py
simpleruleengine/operator/equal.py
simpleruleengine/operator/greater_than.py
simpleruleengine/operator/greater_than_equal.py
simpleruleengine/operator/less_than.py
simpleruleengine/operator/less_than_equal.py
simpleruleengine/operator/not_equal.py
simpleruleengine/operator/numeric_operator.py
simpleruleengine/operator/operator.py
simpleruleengine/operator/string_in.py
simpleruleengine/operator/string_not_in.py
simpleruleengine/operator/string_operator.py
simpleruleengine/rule/__init__.py
simpleruleengine/rule/rule.py
simpleruleengine/rule/rule_decision.py
simpleruleengine/rule/rule_score.py
simpleruleengine/rulerow/__init__.py
simpleruleengine/rulerow/rule_row_decision.py
simpleruleengine/rulerow/rule_row_score.py
simpleruleengine/ruleset/__init__.py
simpleruleengine/ruleset/rule_set_decision.py
simpleruleengine/ruleset/rule_set_score.py
simpleruleengine/token/__init__.py
simpleruleengine/token/boolean_token.py
simpleruleengine/token/numeric_token.py
simpleruleengine/token/rule_token.py
simpleruleengine-2.0.3.dist-info/LICENSE
simpleruleengine-2.0.3.dist-info/METADATA
simpleruleengine-2.0.3.dist-info/WHEEL
simpleruleengine-2.0.3.dist-info/top_level.txt
simpleruleengine-2.0.3.dist-info/RECORD
