Metadata-Version: 2.1
Name: simpleruleengine
Version: 2.0.3
Summary: A lightweight rule engine that allows declarative specification of business rules.
Author-email: Jeyabalaji Subramanian <jeyabalaji.subramanian@gmail.com>
Project-URL: Homepage, https://github.com/jeyabalajis/simple-rule-engine
Project-URL: Bug Tracker, https://github.com/jeyabalajis/simple-rule-engine/issues
Classifier: Programming Language :: Python :: 3
Classifier: License :: OSI Approved :: MIT License
Classifier: Operating System :: OS Independent
Requires-Python: >=3.7
License-File: LICENSE
